LICENSE.txt
MANIFEST.in
README.md
cli.py
hbd.py
setup.py
hbd.egg-info/PKG-INFO
hbd.egg-info/SOURCES.txt
hbd.egg-info/dependency_links.txt
hbd.egg-info/entry_points.txt
hbd.egg-info/requires.txt
hbd.egg-info/top_level.txt