Metadata-Version: 1.0
Name: hbd
Version: 0.2.2
Summary: API and CLI for Humble Bundle downloads.
Home-page: UNKNOWN
Author: David Powell
Author-email: BitLooter@users.noreply.github.com
License: LGPL3
Platform: UNKNOWN
